sphinx_vb_domain/__init__.py
sphinx_vb_domain/utils.py
sphinx_vb_domain/vb_autodoc.py
sphinx_vb_domain/vb_domain.py
sphinx_vb_domain-0.8.2.dist-info/METADATA
sphinx_vb_domain-0.8.2.dist-info/WHEEL
sphinx_vb_domain-0.8.2.dist-info/licenses/LICENSE
sphinx_vb_domain-0.8.2.dist-info/RECORD
