Metadata-Version: 2.1
Name: sphinx-vb-domain
Version: 0.8.2
Summary: Sphinx extension to handle Visual Basic Domain.
Project-URL: Homepage, https://github.com/satamame/sphinx-vb-domain
Project-URL: Repository, https://github.com/satamame/sphinx-vb-domain.git
Project-URL: Issues, https://github.com/satamame/sphinx-vb-domain/issues
Project-URL: Changelog, https://github.com/satamame/sphinx-vb-domain/releases
Author-email: satamame <satamame@gmail.com>
License: MIT
License-File: LICENSE
Keywords: extension,sphinx,vb,visual basic
Classifier: Development Status :: 4 - Beta
Classifier: Framework :: Sphinx
Classifier: Framework :: Sphinx :: Extension
Classifier: License :: OSI Approved :: MIT License
Classifier: Programming Language :: Python :: 3
Requires-Python: >=3.8
Requires-Dist: sphinx>=8.1.3
